MANIFEST.in
README.md
requirements-dev.txt
requirements.txt
setup.py
libcnmc/__init__.py
libcnmc/checker.py
libcnmc/cli.py
libcnmc/cli_4131.py
libcnmc/cli_4666.py
libcnmc/cli_4667.py
libcnmc/cli_4_2015.py
libcnmc/cli_6181.py
libcnmc/cli_8_2021.py
libcnmc/utils.py
libcnmc.egg-info/PKG-INFO
libcnmc.egg-info/SOURCES.txt
libcnmc.egg-info/dependency_links.txt
libcnmc.egg-info/entry_points.txt
libcnmc.egg-info/requires.txt
libcnmc.egg-info/top_level.txt
libcnmc/audit_6181/CTS.py
libcnmc/audit_6181/DES.py
libcnmc/audit_6181/FIA.py
libcnmc/audit_6181/LAT.py
libcnmc/audit_6181/LBT.py
libcnmc/audit_6181/MAQ.py
libcnmc/audit_6181/POS.py
libcnmc/audit_6181/SE.py
libcnmc/audit_6181/__init__.py
libcnmc/cir_3_2015/F3.py
libcnmc/cir_3_2015/__init__.py
libcnmc/cir_4_2014/F1.py
libcnmc/cir_4_2014/F11.py
libcnmc/cir_4_2014/F1bis.py
libcnmc/cir_4_2014/__init__.py
libcnmc/cir_4_2015/F1.py
libcnmc/cir_4_2015/F10AT.py
libcnmc/cir_4_2015/F10BT.py
libcnmc/cir_4_2015/F11.py
libcnmc/cir_4_2015/F12.py
libcnmc/cir_4_2015/F12bis.py
libcnmc/cir_4_2015/F13.py
libcnmc/cir_4_2015/F13C.py
libcnmc/cir_4_2015/F13bis.py
libcnmc/cir_4_2015/F14.py
libcnmc/cir_4_2015/F15.py
libcnmc/cir_4_2015/F16.py
libcnmc/cir_4_2015/F1bis.py
libcnmc/cir_4_2015/F20.py
libcnmc/cir_4_2015/F9.py
libcnmc/cir_4_2015/__init__.py
libcnmc/cir_4_2015/create_celles.py
libcnmc/cir_8_2021/FA1.py
libcnmc/cir_8_2021/FA2.py
libcnmc/cir_8_2021/FA3.py
libcnmc/cir_8_2021/FA4.py
libcnmc/cir_8_2021/FA5.py
libcnmc/cir_8_2021/FB1.py
libcnmc/cir_8_2021/FB1_1.py
libcnmc/cir_8_2021/FB2.py
libcnmc/cir_8_2021/FB2_1.py
libcnmc/cir_8_2021/FB2_2.py
libcnmc/cir_8_2021/FB3.py
libcnmc/cir_8_2021/FB3_1.py
libcnmc/cir_8_2021/FB3_2.py
libcnmc/cir_8_2021/FB3_3.py
libcnmc/cir_8_2021/FB4.py
libcnmc/cir_8_2021/FB5.py
libcnmc/cir_8_2021/FB6.py
libcnmc/cir_8_2021/FB7.py
libcnmc/cir_8_2021/FB8.py
libcnmc/cir_8_2021/FB9.py
libcnmc/cir_8_2021/FC1.py
libcnmc/cir_8_2021/FC2.py
libcnmc/cir_8_2021/FC3.py
libcnmc/cir_8_2021/FC4.py
libcnmc/cir_8_2021/FC5.py
libcnmc/cir_8_2021/FC6.py
libcnmc/cir_8_2021/FC7.py
libcnmc/cir_8_2021/FD1.py
libcnmc/cir_8_2021/FD2.py
libcnmc/cir_8_2021/FF1.py
libcnmc/cir_8_2021/__init__.py
libcnmc/core/__init__.py
