Metadata-Version: 1.1
Name: libcnmc
Version: 25.4.0
Summary: Generació fitxers CNMC
Home-page: http://www.gisce.net
Author: GISCE-TI, S.L.
Author-email: devel@gisce.net
License: General Public Licence 2
Platform: UNKNOWN
Provides: libcnmc
